LSTM_SAM_TL/__init__.py
LSTM_SAM_TL/layers.py
LSTM_SAM_TL/transfer_learning_predict.py
LSTM_SAM_TL/transfer_learning_test.py
LSTM_SAM_TL/tscv_model.py
LSTM_SAM_TL/tt_model.py
LSTM_SAM_TL/utils.py
LSTM_SAM_TL-0.2.4.dist-info/METADATA
LSTM_SAM_TL-0.2.4.dist-info/WHEEL
LSTM_SAM_TL-0.2.4.dist-info/top_level.txt
LSTM_SAM_TL-0.2.4.dist-info/RECORD
