Metadata-Version: 2.1
Name: LSTM-SAM-TL
Version: 0.2.4
Summary: A Python package for developing extreme water level prediction models using a Bi-LSTM architecture with custom attention, designed to transfer trained models across gauging stations.
Author: Samuel Daramola
License: MIT
Project-URL: Homepage, https://pypi.org/project/LSTM-SAM-TL/
Classifier: Programming Language :: Python :: 3
Classifier: License :: OSI Approved :: MIT License
Classifier: Operating System :: OS Independent
Classifier: Topic :: Scientific/Engineering :: Artificial Intelligence
Requires-Python: >=3.9
Requires-Dist: numpy
Requires-Dist: pandas
Requires-Dist: matplotlib
Requires-Dist: scipy
Requires-Dist: scikit-learn
Requires-Dist: tensorflow (>=2.9)
Requires-Dist: keras-tuner (>=1.4.0)
